Workbook

Sheet Start here
A1: Start here — your fees
A2: These are starting points, not gospel. Change every one to match what your platform actually charges you.
A4: Currency | B4: CAD | C4: Label only — this sheet does not convert currencies.
A5: Platform fee % | B5: 0.065 | C5: Etsy transaction fee. Change to your platform's.
A6: Payment processing % | B6: 0.03 | C6: Varies a lot by country. Check yours.
A7: Payment processing fixed | B7: 0.25 | C7: Charged per order.
A8: Listing fee | B8: 0.2 | C8: Per listing. Set 0 if your platform has none.
A9: Shipping you absorb | B9: 8 | C9: Worst case, not average. The one people forget.
A10: Minimum profit per sale | B10: 1 | C10: Your cushion. Not a fee — your floor above zero.
A11: Offsite Ads % | B11: 0 | C11: Only on ad-attributed orders. 0 if you opted out.
A13: Total % fees | B13: =B5+B6+B11 | C13: Platform + processing + offsite ads. Shown so you can sanity-check it.
A15: What this is not
A16: A calculator, not accounting or tax advice. It does not file anything or know your local rules.

Sheet Price floor
A1: What is the lowest price I can sell this at?
A2: Type what the item costs you. Everything else comes from Start here.
A4: What the item costs you | B4: 6 | C4: Wholesale / print cost. Not including shipping.
A6: Your price floor | B6: =(B4+'Start here'!B9+('Start here'!B7+'Start here'!B8)+'Start here'!B10)/(1-'Start here'!B13) | C6: Sell below this and the sale loses money once every fee is counted.
A8: Your actual price | B8: 12
A9: Profit per sale at that price | B9: =B8*(1-'Start here'!B13)-('Start here'!B7+'Start here'!B8)-'Start here'!B9-B4
A11: Verdict | B11: =IF(B8>=B6, "SAFE", "LOSES " & TEXT(ABS(B9),"0.00") & " A SALE") | C11: Red is the whole point of this sheet. A 2x markup goes red more often than anyone expects.

Sheet Your products
A1: Every product, checked against its own floor
A3: SKU | B3: Name | C3: Cost | D3: Shipping (blank = default) | E3: Your price | F3: Floor | G3: Profit/sale | H3: Verdict
F4: =IF(C4="","",(C4+IF(D4="",'Start here'!B9,D4)+('Start here'!B7+'Start here'!B8)+'Start here'!B10)/(1-'Start here'!B13)) | G4: =IF(OR(C4="",E4=""),"",E4*(1-'Start here'!B13)-('Start here'!B7+'Start here'!B8)-IF(D4="",'Start here'!B9,D4)-C4) | H4: =IF(OR(C4="",E4=""),"",IF(E4>=F4,"SAFE","LOSES "&TEXT(ABS(G4),"0.00")))
F5: =IF(C5="","",(C5+IF(D5="",'Start here'!B9,D5)+('Start here'!B7+'Start here'!B8)+'Start here'!B10)/(1-'Start here'!B13)) | G5: =IF(OR(C5="",E5=""),"",E5*(1-'Start here'!B13)-('Start here'!B7+'Start here'!B8)-IF(D5="",'Start here'!B9,D5)-C5) | H5: =IF(OR(C5="",E5=""),"",IF(E5>=F5,"SAFE","LOSES "&TEXT(ABS(G5),"0.00")))
F6: =IF(C6="","",(C6+IF(D6="",'Start here'!B9,D6)+('Start here'!B7+'Start here'!B8)+'Start here'!B10)/(1-'Start here'!B13)) | G6: =IF(OR(C6="",E6=""),"",E6*(1-'Start here'!B13)-('Start here'!B7+'Start here'!B8)-IF(D6="",'Start here'!B9,D6)-C6) | H6: =IF(OR(C6="",E6=""),"",IF(E6>=F6,"SAFE","LOSES "&TEXT(ABS(G6),"0.00")))
F7: =IF(C7="","",(C7+IF(D7="",'Start here'!B9,D7)+('Start here'!B7+'Start here'!B8)+'Start here'!B10)/(1-'Start here'!B13)) | G7: =IF(OR(C7="",E7=""),"",E7*(1-'Start here'!B13)-('Start here'!B7+'Start here'!B8)-IF(D7="",'Start here'!B9,D7)-C7) | H7: =IF(OR(C7="",E7=""),"",IF(E7>=F7,"SAFE","LOSES "&TEXT(ABS(G7),"0.00")))
F8: =IF(C8="","",(C8+IF(D8="",'Start here'!B9,D8)+('Start here'!B7+'Start here'!B8)+'Start here'!B10)/(1-'Start here'!B13)) | G8: =IF(OR(C8="",E8=""),"",E8*(1-'Start here'!B13)-('Start here'!B7+'Start here'!B8)-IF(D8="",'Start here'!B9,D8)-C8) | H8: =IF(OR(C8="",E8=""),"",IF(E8>=F8,"SAFE","LOSES "&TEXT(ABS(G8),"0.00")))
F9: =IF(C9="","",(C9+IF(D9="",'Start here'!B9,D9)+('Start here'!B7+'Start here'!B8)+'Start here'!B10)/(1-'Start here'!B13)) | G9: =IF(OR(C9="",E9=""),"",E9*(1-'Start here'!B13)-('Start here'!B7+'Start here'!B8)-IF(D9="",'Start here'!B9,D9)-C9) | H9: =IF(OR(C9="",E9=""),"",IF(E9>=F9,"SAFE","LOSES "&TEXT(ABS(G9),"0.00")))
F10: =IF(C10="","",(C10+IF(D10="",'Start here'!B9,D10)+('Start here'!B7+'Start here'!B8)+'Start here'!B10)/(1-'Start here'!B13)) | G10: =IF(OR(C10="",E10=""),"",E10*(1-'Start here'!B13)-('Start here'!B7+'Start here'!B8)-IF(D10="",'Start here'!B9,D10)-C10) | H10: =IF(OR(C10="",E10=""),"",IF(E10>=F10,"SAFE","LOSES "&TEXT(ABS(G10),"0.00")))
F11: =IF(C11="","",(C11+IF(D11="",'Start here'!B9,D11)+('Start here'!B7+'Start here'!B8)+'Start here'!B10)/(1-'Start here'!B13)) | G11: =IF(OR(C11="",E11=""),"",E11*(1-'Start here'!B13)-('Start here'!B7+'Start here'!B8)-IF(D11="",'Start here'!B9,D11)-C11) | H11: =IF(OR(C11="",E11=""),"",IF(E11>=F11,"SAFE","LOSES "&TEXT(ABS(G11),"0.00")))
F12: =IF(C12="","",(C12+IF(D12="",'Start here'!B9,D12)+('Start here'!B7+'Start here'!B8)+'Start here'!B10)/(1-'Start here'!B13)) | G12: =IF(OR(C12="",E12=""),"",E12*(1-'Start here'!B13)-('Start here'!B7+'Start here'!B8)-IF(D12="",'Start here'!B9,D12)-C12) | H12: =IF(OR(C12="",E12=""),"",IF(E12>=F12,"SAFE","LOSES "&TEXT(ABS(G12),"0.00")))
F13: =IF(C13="","",(C13+IF(D13="",'Start here'!B9,D13)+('Start here'!B7+'Start here'!B8)+'Start here'!B10)/(1-'Start here'!B13)) | G13: =IF(OR(C13="",E13=""),"",E13*(1-'Start here'!B13)-('Start here'!B7+'Start here'!B8)-IF(D13="",'Start here'!B9,D13)-C13) | H13: =IF(OR(C13="",E13=""),"",IF(E13>=F13,"SAFE","LOSES "&TEXT(ABS(G13),"0.00")))
F14: =IF(C14="","",(C14+IF(D14="",'Start here'!B9,D14)+('Start here'!B7+'Start here'!B8)+'Start here'!B10)/(1-'Start here'!B13)) | G14: =IF(OR(C14="",E14=""),"",E14*(1-'Start here'!B13)-('Start here'!B7+'Start here'!B8)-IF(D14="",'Start here'!B9,D14)-C14) | H14: =IF(OR(C14="",E14=""),"",IF(E14>=F14,"SAFE","LOSES "&TEXT(ABS(G14),"0.00")))
F15: =IF(C15="","",(C15+IF(D15="",'Start here'!B9,D15)+('Start here'!B7+'Start here'!B8)+'Start here'!B10)/(1-'Start here'!B13)) | G15: =IF(OR(C15="",E15=""),"",E15*(1-'Start here'!B13)-('Start here'!B7+'Start here'!B8)-IF(D15="",'Start here'!B9,D15)-C15) | H15: =IF(OR(C15="",E15=""),"",IF(E15>=F15,"SAFE","LOSES "&TEXT(ABS(G15),"0.00")))
F16: =IF(C16="","",(C16+IF(D16="",'Start here'!B9,D16)+('Start here'!B7+'Start here'!B8)+'Start here'!B10)/(1-'Start here'!B13)) | G16: =IF(OR(C16="",E16=""),"",E16*(1-'Start here'!B13)-('Start here'!B7+'Start here'!B8)-IF(D16="",'Start here'!B9,D16)-C16) | H16: =IF(OR(C16="",E16=""),"",IF(E16>=F16,"SAFE","LOSES "&TEXT(ABS(G16),"0.00")))
F17: =IF(C17="","",(C17+IF(D17="",'Start here'!B9,D17)+('Start here'!B7+'Start here'!B8)+'Start here'!B10)/(1-'Start here'!B13)) | G17: =IF(OR(C17="",E17=""),"",E17*(1-'Start here'!B13)-('Start here'!B7+'Start here'!B8)-IF(D17="",'Start here'!B9,D17)-C17) | H17: =IF(OR(C17="",E17=""),"",IF(E17>=F17,"SAFE","LOSES "&TEXT(ABS(G17),"0.00")))
F18: =IF(C18="","",(C18+IF(D18="",'Start here'!B9,D18)+('Start here'!B7+'Start here'!B8)+'Start here'!B10)/(1-'Start here'!B13)) | G18: =IF(OR(C18="",E18=""),"",E18*(1-'Start here'!B13)-('Start here'!B7+'Start here'!B8)-IF(D18="",'Start here'!B9,D18)-C18) | H18: =IF(OR(C18="",E18=""),"",IF(E18>=F18,"SAFE","LOSES "&TEXT(ABS(G18),"0.00")))
F19: =IF(C19="","",(C19+IF(D19="",'Start here'!B9,D19)+('Start here'!B7+'Start here'!B8)+'Start here'!B10)/(1-'Start here'!B13)) | G19: =IF(OR(C19="",E19=""),"",E19*(1-'Start here'!B13)-('Start here'!B7+'Start here'!B8)-IF(D19="",'Start here'!B9,D19)-C19) | H19: =IF(OR(C19="",E19=""),"",IF(E19>=F19,"SAFE","LOSES "&TEXT(ABS(G19),"0.00")))
F20: =IF(C20="","",(C20+IF(D20="",'Start here'!B9,D20)+('Start here'!B7+'Start here'!B8)+'Start here'!B10)/(1-'Start here'!B13)) | G20: =IF(OR(C20="",E20=""),"",E20*(1-'Start here'!B13)-('Start here'!B7+'Start here'!B8)-IF(D20="",'Start here'!B9,D20)-C20) | H20: =IF(OR(C20="",E20=""),"",IF(E20>=F20,"SAFE","LOSES "&TEXT(ABS(G20),"0.00")))
F21: =IF(C21="","",(C21+IF(D21="",'Start here'!B9,D21)+('Start here'!B7+'Start here'!B8)+'Start here'!B10)/(1-'Start here'!B13)) | G21: =IF(OR(C21="",E21=""),"",E21*(1-'Start here'!B13)-('Start here'!B7+'Start here'!B8)-IF(D21="",'Start here'!B9,D21)-C21) | H21: =IF(OR(C21="",E21=""),"",IF(E21>=F21,"SAFE","LOSES "&TEXT(ABS(G21),"0.00")))
F22: =IF(C22="","",(C22+IF(D22="",'Start here'!B9,D22)+('Start here'!B7+'Start here'!B8)+'Start here'!B10)/(1-'Start here'!B13)) | G22: =IF(OR(C22="",E22=""),"",E22*(1-'Start here'!B13)-('Start here'!B7+'Start here'!B8)-IF(D22="",'Start here'!B9,D22)-C22) | H22: =IF(OR(C22="",E22=""),"",IF(E22>=F22,"SAFE","LOSES "&TEXT(ABS(G22),"0.00")))
F23: =IF(C23="","",(C23+IF(D23="",'Start here'!B9,D23)+('Start here'!B7+'Start here'!B8)+'Start here'!B10)/(1-'Start here'!B13)) | G23: =IF(OR(C23="",E23=""),"",E23*(1-'Start here'!B13)-('Start here'!B7+'Start here'!B8)-IF(D23="",'Start here'!B9,D23)-C23) | H23: =IF(OR(C23="",E23=""),"",IF(E23>=F23,"SAFE","LOSES "&TEXT(ABS(G23),"0.00")))
F24: =IF(C24="","",(C24+IF(D24="",'Start here'!B9,D24)+('Start here'!B7+'Start here'!B8)+'Start here'!B10)/(1-'Start here'!B13)) | G24: =IF(OR(C24="",E24=""),"",E24*(1-'Start here'!B13)-('Start here'!B7+'Start here'!B8)-IF(D24="",'Start here'!B9,D24)-C24) | H24: =IF(OR(C24="",E24=""),"",IF(E24>=F24,"SAFE","LOSES "&TEXT(ABS(G24),"0.00")))
F25: =IF(C25="","",(C25+IF(D25="",'Start here'!B9,D25)+('Start here'!B7+'Start here'!B8)+'Start here'!B10)/(1-'Start here'!B13)) | G25: =IF(OR(C25="",E25=""),"",E25*(1-'Start here'!B13)-('Start here'!B7+'Start here'!B8)-IF(D25="",'Start here'!B9,D25)-C25) | H25: =IF(OR(C25="",E25=""),"",IF(E25>=F25,"SAFE","LOSES "&TEXT(ABS(G25),"0.00")))
F26: =IF(C26="","",(C26+IF(D26="",'Start here'!B9,D26)+('Start here'!B7+'Start here'!B8)+'Start here'!B10)/(1-'Start here'!B13)) | G26: =IF(OR(C26="",E26=""),"",E26*(1-'Start here'!B13)-('Start here'!B7+'Start here'!B8)-IF(D26="",'Start here'!B9,D26)-C26) | H26: =IF(OR(C26="",E26=""),"",IF(E26>=F26,"SAFE","LOSES "&TEXT(ABS(G26),"0.00")))
F27: =IF(C27="","",(C27+IF(D27="",'Start here'!B9,D27)+('Start here'!B7+'Start here'!B8)+'Start here'!B10)/(1-'Start here'!B13)) | G27: =IF(OR(C27="",E27=""),"",E27*(1-'Start here'!B13)-('Start here'!B7+'Start here'!B8)-IF(D27="",'Start here'!B9,D27)-C27) | H27: =IF(OR(C27="",E27=""),"",IF(E27>=F27,"SAFE","LOSES "&TEXT(ABS(G27),"0.00")))
F28: =IF(C28="","",(C28+IF(D28="",'Start here'!B9,D28)+('Start here'!B7+'Start here'!B8)+'Start here'!B10)/(1-'Start here'!B13)) | G28: =IF(OR(C28="",E28=""),"",E28*(1-'Start here'!B13)-('Start here'!B7+'Start here'!B8)-IF(D28="",'Start here'!B9,D28)-C28) | H28: =IF(OR(C28="",E28=""),"",IF(E28>=F28,"SAFE","LOSES "&TEXT(ABS(G28),"0.00")))
F29: =IF(C29="","",(C29+IF(D29="",'Start here'!B9,D29)+('Start here'!B7+'Start here'!B8)+'Start here'!B10)/(1-'Start here'!B13)) | G29: =IF(OR(C29="",E29=""),"",E29*(1-'Start here'!B13)-('Start here'!B7+'Start here'!B8)-IF(D29="",'Start here'!B9,D29)-C29) | H29: =IF(OR(C29="",E29=""),"",IF(E29>=F29,"SAFE","LOSES "&TEXT(ABS(G29),"0.00")))
F30: =IF(C30="","",(C30+IF(D30="",'Start here'!B9,D30)+('Start here'!B7+'Start here'!B8)+'Start here'!B10)/(1-'Start here'!B13)) | G30: =IF(OR(C30="",E30=""),"",E30*(1-'Start here'!B13)-('Start here'!B7+'Start here'!B8)-IF(D30="",'Start here'!B9,D30)-C30) | H30: =IF(OR(C30="",E30=""),"",IF(E30>=F30,"SAFE","LOSES "&TEXT(ABS(G30),"0.00")))
F31: =IF(C31="","",(C31+IF(D31="",'Start here'!B9,D31)+('Start here'!B7+'Start here'!B8)+'Start here'!B10)/(1-'Start here'!B13)) | G31: =IF(OR(C31="",E31=""),"",E31*(1-'Start here'!B13)-('Start here'!B7+'Start here'!B8)-IF(D31="",'Start here'!B9,D31)-C31) | H31: =IF(OR(C31="",E31=""),"",IF(E31>=F31,"SAFE","LOSES "&TEXT(ABS(G31),"0.00")))
F32: =IF(C32="","",(C32+IF(D32="",'Start here'!B9,D32)+('Start here'!B7+'Start here'!B8)+'Start here'!B10)/(1-'Start here'!B13)) | G32: =IF(OR(C32="",E32=""),"",E32*(1-'Start here'!B13)-('Start here'!B7+'Start here'!B8)-IF(D32="",'Start here'!B9,D32)-C32) | H32: =IF(OR(C32="",E32=""),"",IF(E32>=F32,"SAFE","LOSES "&TEXT(ABS(G32),"0.00")))
F33: =IF(C33="","",(C33+IF(D33="",'Start here'!B9,D33)+('Start here'!B7+'Start here'!B8)+'Start here'!B10)/(1-'Start here'!B13)) | G33: =IF(OR(C33="",E33=""),"",E33*(1-'Start here'!B13)-('Start here'!B7+'Start here'!B8)-IF(D33="",'Start here'!B9,D33)-C33) | H33: =IF(OR(C33="",E33=""),"",IF(E33>=F33,"SAFE","LOSES "&TEXT(ABS(G33),"0.00")))
A35: Add rows as you need them — the formulas copy down.

Sheet Ads
A1: What do ads have to return before they pay for themselves?
A3: Your price | B3: ='Price floor'!B8
A4: Profit per sale | B4: ='Price floor'!B9
A6: Break-even ROAS | B6: =IF(B4<=0,"n/a — you lose money before ads",B3/B4) | C6: Every $1 of ads must bring back this much in sales just to break even. Below it you are donating.

Sheet This month
A1: Did I make money this month?
A3: Revenue | B3: 0 | C3: Processors usually keep the fixed fee on a refunded order. Count it.
A4: Platform + processing fees | B4: 0
A5: Cost of goods | B5: 0
A6: Shipping you paid | B6: 0
A7: Refunds and chargebacks | B7: 0
A8: Ad spend | B8: 0
A10: Actually made | B10: =B3-B4-B5-B6-B7-B8
A12: Set aside for tax | B12: 0.25
A13: Put this much away | B13: =MAX(0,B10)*B12 | C13: A bucket, not tax advice. Your rate is yours.
